fuzzyutils/__init__.py
fuzzyutils/console.py
fuzzyutils/constants.py
fuzzyutils/print.py
pyrotools/__init__.py
pyrotools/_constants.py
pyrotools/console.py
pyrotools/constants.py
pyrotools/log.py
pyrotools/print.py
pyrotools-1.0.1.dist-info/LICENSE.txt
pyrotools-1.0.1.dist-info/METADATA
pyrotools-1.0.1.dist-info/WHEEL
pyrotools-1.0.1.dist-info/top_level.txt
pyrotools-1.0.1.dist-info/RECORD
